LICENCE.txt
MANIFEST.in
README.md
setup.py
PyPI/long_description.md
causalflow/CPrinter.py
causalflow/__init__.py
causalflow/version.py
causalflow/basics/__init__.py
causalflow/basics/constants.py
causalflow/basics/logger.py
causalflow/basics/metrics.py
causalflow/basics/utils.py
causalflow/causal_discovery/CAnDOIT.py
causalflow/causal_discovery/CausalDiscoveryMethod.py
causalflow/causal_discovery/FPCMCI.py
causalflow/causal_discovery/__init__.py
causalflow/causal_discovery/baseline/DYNOTEARS.py
causalflow/causal_discovery/baseline/JPCMCIplus.py
causalflow/causal_discovery/baseline/LPCMCI.py
causalflow/causal_discovery/baseline/PCMCI.py
causalflow/causal_discovery/baseline/PCMCIplus.py
causalflow/causal_discovery/baseline/TCDF.py
causalflow/causal_discovery/baseline/VarLiNGAM.py
causalflow/causal_discovery/baseline/__init__.py
causalflow/causal_discovery/baseline/tsFCI.py
causalflow/causal_discovery/baseline/pkgs/__init__.py
causalflow/causal_discovery/baseline/pkgs/utils.py
causalflow/causal_discovery/support/__init__.py
causalflow/causal_discovery/support/myLPCMCI.py
causalflow/causal_discovery/support/myPCMCI.py
causalflow/causal_discovery/tigramite/__init__.py
causalflow/causal_discovery/tigramite/causal_effects.py
causalflow/causal_discovery/tigramite/causal_mediation.py
causalflow/causal_discovery/tigramite/data_processing.py
causalflow/causal_discovery/tigramite/jpcmciplus.py
causalflow/causal_discovery/tigramite/lpcmci.py
causalflow/causal_discovery/tigramite/models.py
causalflow/causal_discovery/tigramite/mylpcmci.py
causalflow/causal_discovery/tigramite/pcmci.py
causalflow/causal_discovery/tigramite/pcmci_base.py
causalflow/causal_discovery/tigramite/plotting.py
causalflow/causal_discovery/tigramite/rpcmci.py
causalflow/causal_discovery/tigramite/independence_tests/LBFGS.py
causalflow/causal_discovery/tigramite/independence_tests/__init__.py
causalflow/causal_discovery/tigramite/independence_tests/cmiknn.py
py_causalflow.egg-info/PKG-INFO
py_causalflow.egg-info/SOURCES.txt
py_causalflow.egg-info/dependency_links.txt
py_causalflow.egg-info/requires.txt
py_causalflow.egg-info/top_level.txt