Metadata-Version: 2.1
Name: py-causalflow
Version: 4.0.5
Summary: A Collection of Methods for Causal Discovery from Time-series
Home-page: https://github.com/lcastri/causalflow
Author: Luca Castri
Author-email: lucacastri94@gmail.com
Classifier: Development Status :: 4 - Beta
Classifier: Intended Audience :: Science/Research
Classifier: License :: OSI Approved :: GNU General Public License v3 (GPLv3)
Classifier: Programming Language :: Python :: 3
Classifier: Topic :: Scientific/Engineering :: Artificial Intelligence
Requires-Python: >=3
License-File: LICENCE.txt
Requires-Dist: pandas>=1.5.2
Requires-Dist: numba>=0.58.1
Requires-Dist: scipy>=1.3.3
Requires-Dist: networkx>=2.8.6
Requires-Dist: ruptures>=1.1.7
Requires-Dist: scikit_learn>=1.1.3
Requires-Dist: torch>=1.11.0
Requires-Dist: gpytorch>=1.4
Requires-Dist: dcor>=0.5.3
Requires-Dist: h5py>=3.7.0
Requires-Dist: jpype1>=1.5.0
Requires-Dist: mpmath>=1.3.0
Requires-Dist: causalnex
Requires-Dist: lingam
Requires-Dist: pyopencl>=2024.1
Requires-Dist: matplotlib>=3.7.0
Requires-Dist: numpy
Requires-Dist: pgmpy>=0.1.19
Requires-Dist: tigramite>=5.1.0.3
Requires-Dist: rectangle-packer
Requires-Dist: grandalf
